{
    "Jul 2014": [
        "BALKRISIND.NS",
        "KKCL.NS",
        "AJANTPHARM.NS",
        "VSTIND.NS",
        "ECLERX.NS",
        "WIPRO.NS"
    ],
    "Aug 2014": [
        "BALKRISIND.NS",
        "AJANTPHARM.NS",
        "KKCL.NS",
        "ZENSARTECH.NS",
        "ENGINERSIN.NS",
        "VSTIND.NS"
    ],
    "Sep 2014": [
        "VSTIND.NS",
        "NAUKRI.NS",
        "WHIRLPOOL.NS",
        "ATUL.NS",
        "PIDILITIND.NS",
        "BERGEPAINT.NS"
    ],
    "Oct 2014": [
        "RATNAMANI.NS",
        "ZENSARTECH.NS",
        "ASTRAL.NS",
        "BALKRISIND.NS",
        "VSTIND.NS",
        "KKCL.NS"
    ],
    "Nov 2014": [
        "ASTRAL.NS",
        "RATNAMANI.NS",
        "BALKRISIND.NS",
        "ZENSARTECH.NS",
        "AJANTPHARM.NS",
        "VSTIND.NS"
    ],
    "Dec 2014": [
        "ASTRAL.NS",
        "RATNAMANI.NS",
        "VSTIND.NS",
        "BALKRISIND.NS",
        "AJANTPHARM.NS",
        "INFY.NS"
    ],
    "Jan 2015": [
        "AJANTPHARM.NS",
        "RATNAMANI.NS",
        "VSTIND.NS",
        "ASTRAL.NS",
        "BALKRISIND.NS",
        "KKCL.NS"
    ],
    "Feb 2015": [
        "TORNTPHARM.NS",
        "AJANTPHARM.NS",
        "VSTIND.NS",
        "ASTRAL.NS",
        "ZENSARTECH.NS",
        "KKCL.NS"
    ],
    "Mar 2015": [
        "ASTRAL.NS",
        "AJANTPHARM.NS",
        "TORNTPHARM.NS",
        "VSTIND.NS",
        "ZENSARTECH.NS",
        "KKCL.NS"
    ],
    "Apr 2015": [
        "RATNAMANI.NS",
        "TORNTPHARM.NS",
        "VSTIND.NS",
        "ATUL.NS",
        "ECLERX.NS",
        "VINATIORGA.NS"
    ],
    "May 2015": [
        "CENTURYPLY.NS",
        "WHIRLPOOL.NS",
        "RATNAMANI.NS",
        "ICRA.NS",
        "VSTIND.NS",
        "VINATIORGA.NS"
    ],
    "Jun 2015": [
        "ZENSARTECH.NS",
        "VINATIORGA.NS",
        "RATNAMANI.NS",
        "VSTIND.NS",
        "KKCL.NS",
        "JUBLFOOD.NS"
    ],
    "Jul 2015": [
        "BAJFINANCE.NS",
        "VSTIND.NS",
        "VINATIORGA.NS",
        "ZENSARTECH.NS",
        "JUBLFOOD.NS",
        "HINDUNILVR.NS"
    ],
    "Aug 2015": [
        "BAJFINANCE.NS",
        "ZENSARTECH.NS",
        "JUBLFOOD.NS",
        "RATNAMANI.NS",
        "MUNJALSHOW.NS",
        "KKCL.NS"
    ],
    "Sep 2015": [
        "ZENSARTECH.NS",
        "BAJFINANCE.NS",
        "VSTIND.NS",
        "RATNAMANI.NS",
        "KKCL.NS",
        "IGL.NS"
    ],
    "Oct 2015": [
        "BAJFINANCE.NS",
        "RATNAMANI.NS",
        "VSTIND.NS",
        "ECLERX.NS",
        "JUBLFOOD.NS",
        "KKCL.NS"
    ],
    "Nov 2015": [
        "BAJFINANCE.NS",
        "VSTIND.NS",
        "ZENSARTECH.NS",
        "KAJARIACER.NS",
        "IGL.NS",
        "RATNAMANI.NS"
    ],
    "Dec 2015": [
        "VSTIND.NS",
        "ZENSARTECH.NS",
        "BAJFINANCE.NS",
        "KAJARIACER.NS",
        "INFY.NS",
        "COALINDIA.NS"
    ],
    "Jan 2016": [
        "ZENSARTECH.NS",
        "BAJFINANCE.NS",
        "VSTIND.NS",
        "WIPRO.NS",
        "IGL.NS",
        "KKCL.NS"
    ],
    "Feb 2016": [
        "VSTIND.NS",
        "BAJFINANCE.NS",
        "BRITANNIA.NS",
        "ZENSARTECH.NS",
        "KKCL.NS",
        "TORNTPHARM.NS"
    ],
    "Mar 2016": [
        "VSTIND.NS",
        "BAJFINANCE.NS",
        "BAJAJ-AUTO.NS",
        "TORNTPHARM.NS",
        "ZENSARTECH.NS",
        "KAJARIACER.NS"
    ],
    "Apr 2016": [
        "TIDEWATER.NS",
        "BAJFINANCE.NS",
        "VSTIND.NS",
        "IGL.NS",
        "ZENSARTECH.NS",
        "TVSSRICHAK.NS"
    ],
    "May 2016": [
        "VSTIND.NS",
        "TIDEWATER.NS",
        "IGL.NS",
        "BAJFINANCE.NS",
        "ZENSARTECH.NS",
        "HEROMOTOCO.NS"
    ],
    "Jun 2016": [
        "BAJFINANCE.NS",
        "TIDEWATER.NS",
        "IGL.NS",
        "VSTIND.NS",
        "INFY.NS",
        "ZENSARTECH.NS"
    ],
    "Jul 2016": [
        "AVANTIFEED.NS",
        "VSTIND.NS",
        "KAJARIACER.NS",
        "INFY.NS",
        "TIDEWATER.NS",
        "VGUARD.NS"
    ],
    "Aug 2016": [
        "VSTIND.NS",
        "VGUARD.NS",
        "BAJFINANCE.NS",
        "KAJARIACER.NS",
        "HINDZINC.NS",
        "IGL.NS"
    ],
    "Sep 2016": [
        "VSTIND.NS",
        "IGL.NS",
        "BAJFINANCE.NS",
        "HINDZINC.NS",
        "VGUARD.NS",
        "VAKRANGEE.NS"
    ],
    "Oct 2016": [
        "VSTIND.NS",
        "IGL.NS",
        "VGUARD.NS",
        "VAKRANGEE.NS",
        "BAJFINANCE.NS",
        "HINDZINC.NS"
    ],
    "Nov 2016": [
        "VGUARD.NS",
        "IGL.NS",
        "BALKRISIND.NS",
        "HINDZINC.NS",
        "BERGEPAINT.NS",
        "DHANUKA.NS"
    ],
    "Dec 2016": [
        "IGL.NS",
        "HINDZINC.NS",
        "VSTIND.NS",
        "VAKRANGEE.NS",
        "VINATIORGA.NS",
        "BAJFINANCE.NS"
    ],
    "Jan 2017": [
        "VSTIND.NS",
        "VGUARD.NS",
        "IGL.NS",
        "BALKRISIND.NS",
        "VAKRANGEE.NS",
        "BALMLAWRIE.NS"
    ],
    "Feb 2017": [
        "VSTIND.NS",
        "VGUARD.NS",
        "HINDZINC.NS",
        "BALKRISIND.NS",
        "BAJFINANCE.NS",
        "KSCL.NS"
    ],
    "Mar 2017": [
        "VSTIND.NS",
        "VGUARD.NS",
        "VINATIORGA.NS",
        "BALKRISIND.NS",
        "HINDZINC.NS",
        "AVANTIFEED.NS"
    ],
    "Apr 2017": [
        "VSTIND.NS",
        "VGUARD.NS",
        "VINATIORGA.NS",
        "BALKRISIND.NS",
        "RECLTD.NS",
        "AVANTIFEED.NS"
    ],
    "May 2017": [
        "BALKRISIND.NS",
        "RECLTD.NS",
        "VGUARD.NS",
        "NAVNETEDUL.NS",
        "VAKRANGEE.NS",
        "CERA.NS"
    ],
    "Jun 2017": [
        "VSTIND.NS",
        "AVANTIFEED.NS",
        "RECLTD.NS",
        "BALKRISIND.NS",
        "VGUARD.NS",
        "VINATIORGA.NS"
    ],
    "Jul 2017": [
        "VSTIND.NS",
        "RECLTD.NS",
        "AVANTIFEED.NS",
        "VINATIORGA.NS",
        "GREENPLY.NS",
        "HINDZINC.NS"
    ],
    "Aug 2017": [
        "AVANTIFEED.NS",
        "IGL.NS",
        "VINATIORGA.NS",
        "AARTIIND.NS",
        "NAVNETEDUL.NS",
        "RECLTD.NS"
    ],
    "Sep 2017": [
        "AVANTIFEED.NS",
        "VINATIORGA.NS",
        "VSTIND.NS",
        "HINDZINC.NS",
        "BPCL.NS",
        "WIPRO.NS"
    ],
    "Oct 2017": [
        "KRBL.NS",
        "WIPRO.NS",
        "IGL.NS",
        "BALKRISIND.NS",
        "NAVNETEDUL.NS",
        "VGUARD.NS"
    ],
    "Nov 2017": [
        "AVANTIFEED.NS",
        "IGL.NS",
        "WIPRO.NS",
        "BALKRISIND.NS",
        "VINATIORGA.NS",
        "BRITANNIA.NS"
    ],
    "Dec 2017": [
        "AVANTIFEED.NS",
        "IGL.NS",
        "BALKRISIND.NS",
        "WIPRO.NS",
        "VINATIORGA.NS",
        "NBCC.NS"
    ],
    "Jan 2018": [
        "AVANTIFEED.NS",
        "BALKRISIND.NS",
        "PCJEWELLER.NS",
        "IGL.NS",
        "WIPRO.NS",
        "BRITANNIA.NS"
    ],
    "Feb 2018": [
        "AVANTIFEED.NS",
        "BALKRISIND.NS",
        "PCJEWELLER.NS",
        "IGL.NS",
        "HINDUNILVR.NS",
        "AARTIIND.NS"
    ],
    "Mar 2018": [
        "AVANTIFEED.NS",
        "BALKRISIND.NS",
        "PCJEWELLER.NS",
        "BRITANNIA.NS",
        "IGL.NS",
        "AARTIIND.NS"
    ],
    "Apr 2018": [
        "BALKRISIND.NS",
        "BRITANNIA.NS",
        "PCJEWELLER.NS",
        "VAKRANGEE.NS",
        "AARTIIND.NS",
        "BAJFINANCE.NS"
    ],
    "May 2018": [
        "BALKRISIND.NS",
        "TCS.NS",
        "BRITANNIA.NS",
        "AARTIIND.NS",
        "ZENSARTECH.NS",
        "BAJFINANCE.NS"
    ],
    "Jun 2018": [
        "TECHM.NS",
        "BALKRISIND.NS",
        "CHOLAFIN.NS",
        "AVANTIFEED.NS",
        "ZENSARTECH.NS",
        "PERSISTENT.NS"
    ],
    "Jul 2018": [
        "SONATSOFTW.NS",
        "TECHM.NS",
        "BRITANNIA.NS",
        "CHOLAFIN.NS",
        "TCS.NS",
        "RELAXO.NS"
    ],
    "Aug 2018": [
        "SONATSOFTW.NS",
        "BRITANNIA.NS",
        "RELAXO.NS",
        "TECHM.NS",
        "TCS.NS",
        "HINDUNILVR.NS"
    ],
    "Sep 2018": [
        "SONATSOFTW.NS",
        "BRITANNIA.NS",
        "INFY.NS",
        "HINDUNILVR.NS",
        "VINATIORGA.NS",
        "TCS.NS"
    ],
    "Oct 2018": [
        "ZENSARTECH.NS",
        "SONATSOFTW.NS",
        "INFY.NS",
        "TCS.NS",
        "RELAXO.NS",
        "VINATIORGA.NS"
    ],
    "Nov 2018": [
        "INFY.NS",
        "TECHM.NS",
        "SONATSOFTW.NS",
        "ZENSARTECH.NS",
        "APLLTD.NS",
        "AARTIIND.NS"
    ],
    "Dec 2018": [
        "AARTIIND.NS",
        "TECHM.NS",
        "TCS.NS",
        "BRITANNIA.NS",
        "SONATSOFTW.NS",
        "INFY.NS"
    ],
    "Jan 2019": [
        "TECHM.NS",
        "TCS.NS",
        "BRITANNIA.NS",
        "ZENSARTECH.NS",
        "AARTIIND.NS",
        "SONATSOFTW.NS"
    ],
    "Feb 2019": [
        "AARTIIND.NS",
        "INFY.NS",
        "BRITANNIA.NS",
        "TCS.NS",
        "RELAXO.NS",
        "SONATSOFTW.NS"
    ],
    "Mar 2019": [
        "TCS.NS",
        "TECHM.NS",
        "BRITANNIA.NS",
        "RELAXO.NS",
        "COLPAL.NS",
        "AUROPHARMA.NS"
    ],
    "Apr 2019": [
        "VSTIND.NS",
        "TCS.NS",
        "INFY.NS",
        "COLPAL.NS",
        "ZENSARTECH.NS",
        "AUROPHARMA.NS"
    ],
    "May 2019": [
        "VSTIND.NS",
        "AUROPHARMA.NS",
        "INFY.NS",
        "TCS.NS",
        "PCJEWELLER.NS",
        "COLPAL.NS"
    ],
    "Jun 2019": [
        "VSTIND.NS",
        "WIPRO.NS",
        "RELAXO.NS",
        "INFY.NS",
        "AUROPHARMA.NS",
        "APLLTD.NS"
    ],
    "Jul 2019": [
        "VSTIND.NS",
        "SONATSOFTW.NS",
        "INFY.NS",
        "HINDPETRO.NS",
        "CUMMINSIND.NS",
        "TECHM.NS"
    ],
    "Aug 2019": [
        "WIPRO.NS",
        "VINATIORGA.NS",
        "COLPAL.NS",
        "SONATSOFTW.NS",
        "BAJAJ-AUTO.NS",
        "HINDPETRO.NS"
    ],
    "Sep 2019": [
        "WIPRO.NS",
        "BPCL.NS",
        "HINDPETRO.NS",
        "GULFOILLUB.NS",
        "AKZOINDIA.NS",
        "SONATSOFTW.NS"
    ],
    "Oct 2019": [
        "VSTIND.NS",
        "BPCL.NS",
        "HINDPETRO.NS",
        "GULFOILLUB.NS",
        "CHOLAFIN.NS",
        "GARFIBRES.NS"
    ],
    "Nov 2019": [
        "BPCL.NS",
        "VINATIORGA.NS",
        "HINDPETRO.NS",
        "TCS.NS",
        "BAJAJ-AUTO.NS",
        "AVANTIFEED.NS"
    ],
    "Dec 2019": [
        "VSTIND.NS",
        "BPCL.NS",
        "AVANTIFEED.NS",
        "VINATIORGA.NS",
        "INFY.NS",
        "HINDPETRO.NS"
    ],
    "Jan 2020": [
        "VSTIND.NS",
        "AVANTIFEED.NS",
        "BPCL.NS",
        "VINATIORGA.NS",
        "INFY.NS",
        "AARTIIND.NS"
    ],
    "Feb 2020": [
        "VSTIND.NS",
        "AVANTIFEED.NS",
        "VINATIORGA.NS",
        "BPCL.NS",
        "SUDARSCHEM.NS",
        "CHOLAFIN.NS"
    ],
    "Mar 2020": [
        "VSTIND.NS",
        "AARTIIND.NS",
        "AVANTIFEED.NS",
        "BPCL.NS",
        "AJANTPHARM.NS",
        "SUDARSCHEM.NS"
    ],
    "Apr 2020": [
        "VSTIND.NS",
        "AJANTPHARM.NS",
        "SUDARSCHEM.NS",
        "AARTIIND.NS",
        "VINATIORGA.NS",
        "BPCL.NS"
    ],
    "May 2020": [
        "AJANTPHARM.NS",
        "VSTIND.NS",
        "AARTIIND.NS",
        "APLLTD.NS",
        "SUDARSCHEM.NS",
        "AVANTIFEED.NS"
    ],
    "Jun 2020": [
        "AJANTPHARM.NS",
        "APLLTD.NS",
        "SUDARSCHEM.NS",
        "VSTIND.NS",
        "AVANTIFEED.NS",
        "AARTIIND.NS"
    ],
    "Jul 2020": [
        "ALKYLAMINE.NS",
        "BHARATRAS.NS",
        "APLLTD.NS",
        "VSTIND.NS",
        "AVANTIFEED.NS",
        "AJANTPHARM.NS"
    ],
    "Aug 2020": [
        "ALKYLAMINE.NS",
        "APLLTD.NS",
        "BHARATRAS.NS",
        "AVANTIFEED.NS",
        "TATAELXSI.NS",
        "SWARAJENG.NS"
    ],
    "Sep 2020": [
        "ALKYLAMINE.NS",
        "VSTIND.NS",
        "BHARATRAS.NS",
        "AVANTIFEED.NS",
        "AJANTPHARM.NS",
        "TATAELXSI.NS"
    ],
    "Oct 2020": [
        "AARTIDRUGS.NS",
        "ALKYLAMINE.NS",
        "VSTIND.NS",
        "APLLTD.NS",
        "AJANTPHARM.NS",
        "TATAELXSI.NS"
    ],
    "Nov 2020": [
        "AARTIDRUGS.NS",
        "ALKYLAMINE.NS",
        "PERSISTENT.NS",
        "APLLTD.NS",
        "AJANTPHARM.NS",
        "HCLTECH.NS"
    ],
    "Dec 2020": [
        "AARTIDRUGS.NS",
        "PERSISTENT.NS",
        "ALKYLAMINE.NS",
        "VSTIND.NS",
        "CAPLIPOINT.NS",
        "TATAELXSI.NS"
    ],
    "Jan 2021": [
        "AARTIDRUGS.NS",
        "ALKYLAMINE.NS",
        "PERSISTENT.NS",
        "VSTIND.NS",
        "AUROPHARMA.NS",
        "CAPLIPOINT.NS"
    ],
    "Feb 2021": [
        "AARTIDRUGS.NS",
        "ALKYLAMINE.NS",
        "WIPRO.NS",
        "VSTIND.NS",
        "CAPLIPOINT.NS",
        "AUROPHARMA.NS"
    ],
    "Mar 2021": [
        "AARTIDRUGS.NS",
        "ALKYLAMINE.NS",
        "STLTECH.NS",
        "WIPRO.NS",
        "ASAL.NS",
        "HINDZINC.NS"
    ],
    "Apr 2021": [
        "AARTIDRUGS.NS",
        "ALKYLAMINE.NS",
        "VSTIND.NS",
        "JUSTDIAL.NS",
        "STLTECH.NS",
        "KPRMILL.NS"
    ],
    "May 2021": [
        "PERSISTENT.NS",
        "AARTIDRUGS.NS",
        "DCMSHRIRAM.NS",
        "CENTURYPLY.NS",
        "STLTECH.NS",
        "SONATSOFTW.NS"
    ],
    "Jun 2021": [
        "SONATSOFTW.NS",
        "WIPRO.NS",
        "AARTIDRUGS.NS",
        "STLTECH.NS",
        "BEL.NS",
        "ASAL.NS"
    ],
    "Jul 2021": [
        "ASAL.NS",
        "ALKYLAMINE.NS",
        "WIPRO.NS",
        "DCMSHRIRAM.NS",
        "SONATSOFTW.NS",
        "VSTIND.NS"
    ],
    "Aug 2021": [
        "ASAL.NS",
        "DCMSHRIRAM.NS",
        "KNRCON.NS",
        "POLYPLEX.NS",
        "SONATSOFTW.NS",
        "WIPRO.NS"
    ],
    "Sep 2021": [
        "ALKYLAMINE.NS",
        "KNRCON.NS",
        "WIPRO.NS",
        "ASAL.NS",
        "SONATSOFTW.NS",
        "BALRAMCHIN.NS"
    ],
    "Oct 2021": [
        "KPRMILL.NS",
        "DCMSHRIRAM.NS",
        "ASAL.NS",
        "BALRAMCHIN.NS",
        "LUXIND.NS",
        "ALKYLAMINE.NS"
    ],
    "Nov 2021": [
        "ASAL.NS",
        "ALKYLAMINE.NS",
        "SONATSOFTW.NS",
        "KPRMILL.NS",
        "DCMSHRIRAM.NS",
        "BEL.NS"
    ],
    "Dec 2021": [
        "KPRMILL.NS",
        "SONATSOFTW.NS",
        "POLYPLEX.NS",
        "DCMSHRIRAM.NS",
        "KEI.NS",
        "BEL.NS"
    ],
    "Jan 2022": [
        "ASAL.NS",
        "POLYPLEX.NS",
        "KPRMILL.NS",
        "DCMSHRIRAM.NS",
        "LUXIND.NS",
        "WIPRO.NS"
    ],
    "Feb 2022": [
        "KPRMILL.NS",
        "ASAL.NS",
        "BALRAMCHIN.NS",
        "DCMSHRIRAM.NS",
        "POLYPLEX.NS",
        "SONATSOFTW.NS"
    ],
    "Mar 2022": [
        "ASAL.NS",
        "TATAELXSI.NS",
        "RHIM.NS",
        "SFL.NS",
        "CAPLIPOINT.NS",
        "SOLARINDS.NS"
    ],
    "Apr 2022": [
        "ASAL.NS",
        "POLYPLEX.NS",
        "KPRMILL.NS",
        "BALRAMCHIN.NS",
        "KEI.NS",
        "DCMSHRIRAM.NS"
    ],
    "May 2022": [
        "ASAL.NS",
        "POLYPLEX.NS",
        "KPRMILL.NS",
        "CHAMBLFERT.NS",
        "KEI.NS",
        "COALINDIA.NS"
    ],
    "Jun 2022": [
        "ASAL.NS",
        "POLYPLEX.NS",
        "SFL.NS",
        "ECLERX.NS",
        "KEI.NS",
        "BEL.NS"
    ],
    "Jul 2022": [
        "TI.NS",
        "ASAL.NS",
        "PITTIENG.NS",
        "SHARDACROP.NS",
        "GHCL.NS",
        "EKC.NS"
    ],
    "Aug 2022": [
        "TI.NS",
        "ASAL.NS",
        "EKC.NS",
        "DWARKESH.NS",
        "GHCL.NS",
        "BEL.NS"
    ],
    "Sep 2022": [
        "SOLARINDS.NS",
        "COALINDIA.NS",
        "CENTURYPLY.NS",
        "GRINDWELL.NS",
        "SHARDACROP.NS",
        "ZEEL.NS"
    ],
    "Oct 2022": [
        "TI.NS",
        "ASAL.NS",
        "MANGCHEFER.NS",
        "PITTIENG.NS",
        "BEL.NS",
        "GOKUL.NS"
    ],
    "Nov 2022": [
        "ASAL.NS",
        "MANGCHEFER.NS",
        "BEL.NS",
        "PITTIENG.NS",
        "GOKUL.NS",
        "COCHINSHIP.NS"
    ],
    "Dec 2022": [
        "COCHINSHIP.NS",
        "BEL.NS",
        "ASAL.NS",
        "DWARKESH.NS",
        "SALASAR.NS",
        "PITTIENG.NS"
    ],
    "Jan 2023": [
        "FACT.NS",
        "SALASAR.NS",
        "PRECWIRE.NS",
        "UTTAMSUGAR.NS",
        "HINDUNILVR.NS",
        "DWARKESH.NS"
    ],
    "Feb 2023": [
        "FACT.NS",
        "SALASAR.NS",
        "TI.NS",
        "HISARMETAL.NS",
        "GPTINFRA.NS",
        "HINDUNILVR.NS"
    ],
    "Mar 2023": [
        "TI.NS",
        "FACT.NS",
        "SALASAR.NS",
        "GNA.NS",
        "COCHINSHIP.NS",
        "HISARMETAL.NS"
    ],
    "Apr 2023": [
        "HAL.NS",
        "BANCOINDIA.NS",
        "TI.NS",
        "GOKULAGRO.NS",
        "GNA.NS",
        "SONATSOFTW.NS"
    ],
    "May 2023": [
        "MOLDTECH.NS",
        "KAMDHENU.NS",
        "FACT.NS",
        "TVSMOTOR.NS",
        "HAL.NS",
        "ITC.NS"
    ],
    "Jun 2023": [
        "TI.NS",
        "FACT.NS",
        "PRECWIRE.NS",
        "SONATSOFTW.NS",
        "SURYAROSNI.NS",
        "HGINFRA.NS"
    ],
    "Jul 2023": [
        "FACT.NS",
        "REFEX.NS",
        "UGARSUGAR.NS",
        "TI.NS",
        "BANCOINDIA.NS",
        "SONATSOFTW.NS"
    ],
    "Aug 2023": [
        "FACT.NS",
        "REFEX.NS",
        "TI.NS",
        "KAMDHENU.NS",
        "UGARSUGAR.NS",
        "SALASAR.NS"
    ],
    "Sep 2023": [
        "FACT.NS",
        "REFEX.NS",
        "TI.NS",
        "BANCOINDIA.NS",
        "UGARSUGAR.NS",
        "PERSISTENT.NS"
    ],
    "Oct 2023": [
        "MOLDTECH.NS",
        "FACT.NS",
        "PERSISTENT.NS",
        "ZENSARTECH.NS",
        "ASTRAZEN.NS",
        "UGARSUGAR.NS"
    ],
    "Nov 2023": [
        "FACT.NS",
        "NEWGEN.NS",
        "GOKEX.NS",
        "GPIL.NS",
        "SURYAROSNI.NS",
        "PERSISTENT.NS"
    ],
    "Dec 2023": [
        "FACT.NS",
        "TI.NS",
        "BANCOINDIA.NS",
        "MOLDTECH.NS",
        "SONATSOFTW.NS",
        "REFEX.NS"
    ],
    "Jan 2024": [
        "NEWGEN.NS",
        "HAL.NS",
        "FACT.NS",
        "SURYAROSNI.NS",
        "SONATSOFTW.NS",
        "GOKEX.NS"
    ],
    "Feb 2024": [
        "FACT.NS",
        "HAL.NS",
        "RITES.NS",
        "SONATSOFTW.NS",
        "JBCHEPHARM.NS",
        "PCBL.NS"
    ],
    "Mar 2024": [
        "APARINDS.NS",
        "FACT.NS",
        "OFSS.NS",
        "ENGINERSIN.NS",
        "JBCHEPHARM.NS",
        "BAJAJ-AUTO.NS"
    ],
    "Apr 2024": [
        "BANCOINDIA.NS",
        "NEWGEN.NS",
        "FACT.NS",
        "HAL.NS",
        "TI.NS",
        "GOKEX.NS"
    ],
    "May 2024": [
        "BANCOINDIA.NS",
        "JBCHEPHARM.NS",
        "GULFOILLUB.NS",
        "NMDC.NS",
        "HAL.NS",
        "GODFRYPHLP.NS"
    ],
    "Jun 2024": [
        "HAL.NS",
        "JBCHEPHARM.NS",
        "OFSS.NS",
        "NMDC.NS",
        "HINDZINC.NS",
        "FACT.NS"
    ],
    "Jul 2024": [
        "GODFRYPHLP.NS",
        "MSTCLTD.NS",
        "APARINDS.NS",
        "SHARDAMOTR.NS",
        "HINDZINC.NS",
        "BANCOINDIA.NS"
    ],
    "Aug 2024": [
        "SHARDAMOTR.NS",
        "BANCOINDIA.NS",
        "FACT.NS",
        "MSTCLTD.NS",
        "GODFRYPHLP.NS",
        "COALINDIA.NS"
    ],
    "Sep 2024": [
        "SHARDAMOTR.NS",
        "GRANULES.NS",
        "HAL.NS",
        "FACT.NS",
        "COALINDIA.NS",
        "DHANUKA.NS"
    ],
    "Oct 2024": [
        "IIFLSEC.NS",
        "PCBL.NS",
        "SHARDAMOTR.NS",
        "HAL.NS",
        "TI.NS",
        "HINDZINC.NS"
    ],
    "Nov 2024": [
        "IIFLSEC.NS",
        "HINDZINC.NS",
        "APARINDS.NS",
        "HAL.NS",
        "SHARDAMOTR.NS",
        "BAJAJ-AUTO.NS"
    ],
    "Dec 2024": [
        "IIFLSEC.NS",
        "GODFRYPHLP.NS",
        "APARINDS.NS",
        "TI.NS",
        "HINDZINC.NS",
        "HAL.NS"
    ],
    "Jan 2025": [
        "TI.NS",
        "IIFLSEC.NS",
        "APARINDS.NS",
        "GULFOILLUB.NS",
        "HINDZINC.NS",
        "PCBL.NS"
    ],
    "Feb 2025": [
        "TI.NS",
        "MUTHOOTFIN.NS",
        "HINDZINC.NS",
        "OFSS.NS",
        "CHAMBLFERT.NS",
        "GRANULES.NS"
    ],
    "Mar 2025": [
        "DIXON.NS",
        "GODFRYPHLP.NS",
        "IIFLSEC.NS",
        "ZENSARTECH.NS",
        "KSCL.NS",
        "HINDZINC.NS"
    ],
    "Apr 2025": [
        "COROMANDEL.NS",
        "AVANTIFEED.NS",
        "ASTRAZEN.NS",
        "SUVENPHAR.NS",
        "POLYMED.NS",
        "CHAMBLFERT.NS"
    ],
    "May 2025": [
        "GODFRYPHLP.NS",
        "SUVENPHAR.NS",
        "DIXON.NS",
        "KSCL.NS",
        "ASTRAZEN.NS",
        "SOLARINDS.NS"
    ],
    "Jun 2025": [
        "PCBL.NS",
        "TI.NS",
        "ZENSARTECH.NS",
        "CHAMBLFERT.NS",
        "GODREJAGRO.NS",
        "CDSL.NS"
    ],
    "Jul 2025": [
        "REFEX.NS",
        "WELCORP.NS",
        "TI.NS",
        "ECLERX.NS",
        "REDINGTON.NS",
        "HCLTECH.NS"
    ],
    "Aug 2025": [
        "TI.NS",
        "REFEX.NS",
        "WELCORP.NS",
        "REDINGTON.NS",
        "BRITANNIA.NS",
        "MANAPPURAM.NS"
    ],
    "Sep 2025": [
        "TI.NS",
        "GPIL.NS",
        "WELCORP.NS",
        "REDINGTON.NS",
        "IMFA.NS",
        "MANAPPURAM.NS"
    ]
}